disthon/__init__.py
disthon-0.1.0.dist-info/WHEEL
disthon-0.1.0.dist-info/METADATA
disthon-0.1.0.dist-info/RECORD
