Metadata-Version: 2.1
Name: disthon
Version: 0.1.0
Summary: A Discord API wrapper
Author: vcokltfre
Author-email: vcokltfre@gmail.com
Requires-Python: >=3.9,<4.0
Classifier: Programming Language :: Python :: 3
Classifier: Programming Language :: Python :: 3.10
Classifier: Programming Language :: Python :: 3.9
